idgi/__init__.py
idgi/cli.py
idgi/core/__init__.py
idgi/core/analyzer.py
idgi/core/parser.py
idgi/core/scanner.py
idgi/export/__init__.py
idgi/export/formats.py
idgi/graph/__init__.py
idgi/graph/builder.py
idgi/graph/interactive.py
idgi/graph/visualizer.py
idgi/utils/__init__.py
idgi/utils/cache.py
idgi/utils/filters.py
idgi-0.1.1.dist-info/METADATA
idgi-0.1.1.dist-info/WHEEL
idgi-0.1.1.dist-info/entry_points.txt
idgi-0.1.1.dist-info/licenses/LICENSE
idgi-0.1.1.dist-info/RECORD
